{
  "kind": "AppSpec",
  "meta": {
    "id": "726c505ad5b0754e",
    "name": "hooto-press",
    "version": "9"
  },
  "roles": [
    100
  ],
  "packages": [
    {
      "name": "hooto-press",
      "version": "0.2.2.dev",
      "release": "1",
      "dist": "el7",
      "arch": "x64"
    }
  ],
  "executors": [
    {
      "name": "main",
      "exec_start": "DAEMON=/home/action/apps/hooto-press/bin/hooto-press\nDAEMON_ARGS=\"-log_dir=/home/action/apps/hooto-press/var/log -minloglevel=1 -logtolevels=true\"\nNAME=hooto-press\n\nif pidof $NAME; then\n    exit 0\nfi\n\nmkdir -p /home/action/apps/hooto-press/\nrsync -av {{.inpack_prefix_hooto_press}}/* /home/action/apps/hooto-press/\n\n$DAEMON $DAEMON_ARGS \u003e\u003e /home/action/var/log/hooto-press.log 2\u003e\u00261 \u0026\n\nsleep 1\nexit 0",
      "exec_stop": "killall hooto-press",
      "plan": {
        "on_tick": 60
      }
    }
  ],
  "service_ports": [
    {
      "name": "http",
      "box_port": 9533
    }
  ],
  "configurator": {
    "name": "cfg/hooto-press",
    "fields": [
      {
        "name": "iam_service_url",
        "title": "IAM Service URL",
        "type": 1
      },
      {
        "name": "iam_service_url_frontend",
        "title": "IAM Service URL for Frontend",
        "type": 1
      },
      {
        "name": "bound_sysinner_mysql",
        "title": "Bound App",
        "type": 10,
        "default": "cfg/sysinner-mysql"
      }
    ]
  }
}
